{
    "0xa4c138cd256aef56": {
        "state": "OFF",
        "countdown": 0,
        "power_on_behavior": "previous",
        "switch_type": "toggle",
        "linkquality": 58
    },
    "0x00158d00048681f7": {
        "temperature": 19.55,
        "humidity": 61.1,
        "pressure": 1005.7,
        "linkquality": 134,
        "voltage": 2985,
        "battery": 90,
        "power_outage_count": 24354
    },
    "0xa4c138357ecf3e4c": {
        "state_l1": "ON",
        "power_on_behavior_l1": "previous",
        "state_l2": "ON",
        "power_on_behavior_l2": "previous",
        "switch_mode_l1": "switch",
        "switch_mode_l2": "switch",
        "linkquality": 72
    }
}